apialerts/__init__.py
apialerts/apialerts.py
apialerts/client.py
apialerts/constants.py
apialerts/event.py
apialerts/network.py
apialerts-1.1.3.dist-info/LICENSE
apialerts-1.1.3.dist-info/METADATA
apialerts-1.1.3.dist-info/WHEEL
apialerts-1.1.3.dist-info/top_level.txt
apialerts-1.1.3.dist-info/RECORD
