Metadata-Version: 2.2
Name: apialerts
Version: 1.1.3
Summary: Python wrapper for the API Alerts service
Author-email: API Alerts <support@apialerts.com>
License: MIT License
Project-URL: Homepage, https://apialerts.com
Project-URL: Documentation, https://apialerts.com/docs/python
Project-URL: Repository, https://github.com/apialerts/apialerts-python
Project-URL: Issues, https://github.com/apialerts/apialerts-python/issues
Keywords: API Alerts,push,notifications,alert,monitoring
Classifier: Development Status :: 5 - Production/Stable
Classifier: Operating System :: OS Independent
Classifier: Intended Audience :: Developers
Classifier: Natural Language :: English
Classifier: Operating System :: OS Independent
Classifier: Programming Language :: Python :: 3.8
Classifier: Programming Language :: Python :: 3.9
Classifier: Programming Language :: Python :: 3.10
Classifier: Programming Language :: Python :: 3.11
Classifier: Programming Language :: Python :: 3.12
Classifier: Programming Language :: Python :: 3.13
Classifier: License :: OSI Approved :: MIT License
Classifier: Topic :: Internet
Classifier: Topic :: Software Development :: Libraries
Classifier: Topic :: Software Development :: Libraries :: Python Modules
Classifier: Topic :: Utilities
Classifier: Typing :: Typed
Requires-Python: >=3.8
License-File: LICENSE
Requires-Dist: aiohttp<4.0.0,>=3.10.0
Requires-Dist: certifi>=2024.2.2
